strik0rium/Strik0r.py
strik0rium/__init__.py
strik0rium-0.0.2.dist-info/LICENSE
strik0rium-0.0.2.dist-info/METADATA
strik0rium-0.0.2.dist-info/WHEEL
strik0rium-0.0.2.dist-info/top_level.txt
strik0rium-0.0.2.dist-info/RECORD
