Metadata-Version: 2.1
Name: strik0rium
Version: 0.0.2
Summary: A placeholder package for future development
Author: Strik0r
Author-email: strik0rium@gmail.com
Classifier: Programming Language :: Python :: 3
Classifier: License :: OSI Approved :: MIT License
Classifier: Operating System :: OS Independent
Requires-Python: >=3.6
License-File: LICENSE
